typetalk/__init__.py
typetalk/bot.py
typetalk/client.py
typetalk/http.py
typetalk/route.py
typetalk-1.0.3.dist-info/METADATA
typetalk-1.0.3.dist-info/WHEEL
typetalk-1.0.3.dist-info/top_level.txt
typetalk-1.0.3.dist-info/RECORD
