Metadata-Version: 2.1
Name: typetalk
Version: 1.0.3
Summary: Typetalk API client
Home-page: https://github.com/is2ei/typetalk-py
Author: Issei Horie
License: MIT
Platform: UNKNOWN
